{
  "id": "blog/2019-05-29-long-blog-post",
  "title": "Long Blog Post",
  "description": "This is the summary of a very long blog post,",
  "source": "@site/docs/blog/2019-05-29-long-blog-post.md",
  "sourceDirName": "blog",
  "slug": "/blog/long-blog-post",
  "permalink": "/Hackathon-Transpetro/docs/blog/long-blog-post",
  "draft": false,
  "unlisted": false,
  "tags": [
    {
      "inline": true,
      "label": "hello",
      "permalink": "/Hackathon-Transpetro/docs/tags/hello"
    },
    {
      "inline": true,
      "label": "docusaurus",
      "permalink": "/Hackathon-Transpetro/docs/tags/docusaurus"
    }
  ],
  "version": "current",
  "frontMatter": {
    "slug": "long-blog-post",
    "title": "Long Blog Post",
    "authors": "yangshun",
    "tags": [
      "hello",
      "docusaurus"
    ]
  },
  "sidebar": "defaultSidebar",
  "previous": {
    "title": "First Blog Post",
    "permalink": "/Hackathon-Transpetro/docs/blog/first-blog-post"
  },
  "next": {
    "title": "MDX Blog Post",
    "permalink": "/Hackathon-Transpetro/docs/blog/mdx-blog-post"
  }
}